pkgcheck/__init__.py
pkgcheck/__main__.py
pkgcheck/messages.py
pkgcheck/pkgcheck.py
pkgcheck/tests/__init__.py
pkgcheck/tests/base.py
pkgcheck/tests/test_pkgcheck.py
pkgcheck/tests/samples/.E005_excluded
pkgcheck/tests/samples/E001_bad.sh
pkgcheck/tests/samples/E002_bad.sh
pkgcheck/tests/samples/E003_bad.sh
pkgcheck/tests/samples/E003_good.sh
pkgcheck/tests/samples/E004_bad.sh
pkgcheck/tests/samples/E010_bad.sh
pkgcheck/tests/samples/E010_good.sh
pkgcheck/tests/samples/E011_bad.sh
pkgcheck/tests/samples/E011_good.sh
pkgcheck/tests/samples/E012_bad.sh
pkgcheck/tests/samples/E040_syntax_error.sh
pkgcheck/tests/samples/E041_bad.sh
pkgcheck/tests/samples/E044_bad.sh
pkgcheck/tests/samples/W042_bad.sh
pkgcheck/tests/samples/W043_bad.sh
pkgcheck/tests/samples/W063_bad.sh
pkgcheck/tests/samples/comments.sh
pkgcheck/tests/samples/for_loops.sh
pkgcheck/tests/samples/heredoc_ignore.sh
pkgcheck/tests/samples/legacy_sample.sh
pkgcheck_arch-0.1.5.dist-info/licenses/AUTHORS
pkgcheck_arch-0.1.5.dist-info/licenses/LICENSE
pkgcheck_arch-0.1.5.dist-info/METADATA
pkgcheck_arch-0.1.5.dist-info/WHEEL
pkgcheck_arch-0.1.5.dist-info/entry_points.txt
pkgcheck_arch-0.1.5.dist-info/pbr.json
pkgcheck_arch-0.1.5.dist-info/top_level.txt
pkgcheck_arch-0.1.5.dist-info/RECORD
